rubiks_cube_gym/__init__.py
rubiks_cube_gym/envs/__init__.py
rubiks_cube_gym/envs/pyraminx_wo_tips.py
rubiks_cube_gym/envs/pyraminx_wo_tips_lbl.py
rubiks_cube_gym/envs/rubiks_cube_222.py
rubiks_cube_gym/envs/rubiks_cube_222_lbl.py
rubiks_cube_gym/envs/rubiks_cube_222_ortega.py
rubiks_cube_gym/envs/skewb.py
rubiks_cube_gym/envs/skewb_sarah.py
rubiks_cube_gym-0.5.2.dist-info/LICENSE
rubiks_cube_gym-0.5.2.dist-info/METADATA
rubiks_cube_gym-0.5.2.dist-info/WHEEL
rubiks_cube_gym-0.5.2.dist-info/top_level.txt
rubiks_cube_gym-0.5.2.dist-info/RECORD
