Metadata-Version: 2.1
Name: rubiks-cube-gym
Version: 0.5.2
Summary: OpenAI Gym environments for various twisty puzzles
Home-page: https://github.com/DoubleGremlin181/RubiksCubeGym/
Author: Kavish Hukmani
Author-email: khukmani@gmail.com
License: MIT
Keywords: environment,agent,rl,rubiks,cube,openai-gym,gym
License-File: LICENSE
Requires-Dist: gymnasium ==0.29.1
Requires-Dist: numpy
Requires-Dist: opencv-python
Requires-Dist: wget
